reloadr.py
Reloadr-0.4.1.data/scripts/reloadr.py
Reloadr-0.4.1.dist-info/LICENSE
Reloadr-0.4.1.dist-info/METADATA
Reloadr-0.4.1.dist-info/WHEEL
Reloadr-0.4.1.dist-info/top_level.txt
Reloadr-0.4.1.dist-info/RECORD
