Metadata-Version: 2.1
Name: Reloadr
Version: 0.4.1
Summary: Hot code reloading tool for Python
Home-page: https://github.com/hoh/reloadr
Author: Hugo Herter
Author-email: git@hugoherter.com
License: LGPLv3
Keywords: reload hot code reloading
Platform: UNKNOWN
Classifier: Development Status :: 3 - Alpha
Classifier: Programming Language :: Python :: 3
Classifier: Operating System :: POSIX :: Linux
Classifier: Intended Audience :: Developers
Requires-Dist: watchdog
